factcheck/__init__.py
factcheck/__main__.py
factcheck/config/api_config.yaml
factcheck/config/sample_prompt.yaml
factcheck/core/CheckWorthy.py
factcheck/core/ClaimVerify.py
factcheck/core/Decompose.py
factcheck/core/QueryGenerator.py
factcheck/core/Retriever/__init__.py
factcheck/core/Retriever/base.py
factcheck/core/Retriever/google_retriever.py
factcheck/core/Retriever/serper_retriever.py
factcheck/core/__init__.py
factcheck/utils/api_config.py
factcheck/utils/llmclient/__init__.py
factcheck/utils/llmclient/base.py
factcheck/utils/llmclient/claude_client.py
factcheck/utils/llmclient/gpt_client.py
factcheck/utils/llmclient/local_openai_client.py
factcheck/utils/logger.py
factcheck/utils/multimodal.py
factcheck/utils/prompt/__init__.py
factcheck/utils/prompt/base.py
factcheck/utils/prompt/chatgpt_prompt.py
factcheck/utils/prompt/claude_prompt.py
factcheck/utils/prompt/customized_prompt.py
factcheck/utils/utils.py
factcheck/utils/web_util.py
openfactverification_kongzii-0.5.3.dist-info/LICENSE
openfactverification_kongzii-0.5.3.dist-info/METADATA
openfactverification_kongzii-0.5.3.dist-info/WHEEL
openfactverification_kongzii-0.5.3.dist-info/RECORD
