Metadata-Version: 2.1
Name: openfactverification-kongzii
Version: 0.5.3
Summary: Loki: An Open-source Tool for Fact Verification
Home-page: https://github.com/Libr-AI/OpenFactVerification/
License: MIT
Author: Hao Wang
Author-email: hao.wang@librai.tech
Requires-Python: >=3.10,<3.12
Classifier: License :: OSI Approved :: MIT License
Classifier: Programming Language :: Python :: 3
Classifier: Programming Language :: Python :: 3.10
Classifier: Programming Language :: Python :: 3.11
Provides-Extra: api
Requires-Dist: Flask (>=3.0.3,<4.0.0) ; extra == "api"
Requires-Dist: anthropic (>=0.23.1,<1)
Requires-Dist: backoff (>=2.2.1,<3.0.0)
Requires-Dist: bs4 (>=0.0.2,<0.0.3)
Requires-Dist: httpx (>=0.25.1,<1)
Requires-Dist: nltk (>=3.8.1,<4.0.0)
Requires-Dist: openai (>=1.16.2,<2.0.0)
Requires-Dist: opencv-python (>=4.9.0.80,<5.0.0.0)
Requires-Dist: pandas (>=2.2.1,<3.0.0)
Requires-Dist: playwright (>=1.42.0,<2.0.0)
Requires-Dist: playwright-stealth (>=1.0.6,<2.0.0)
Requires-Dist: prediction-market-agent-tooling (>=0.48.11,<1)
Requires-Dist: tiktoken (>=0.6.0,<1.0.0)
Project-URL: Repository, https://github.com/Libr-AI/OpenFactVerification/
